{
  "owner": "ide-rea",
  "slug": "ai-notes-ofvideo",
  "displayName": "Ai Notes Ofvideo",
  "latest": {
    "version": "1.0.10",
    "publishedAt": 1770782033898,
    "commit": null
  },
  "history": [
    {
      "version": "1.0.7",
      "publishedAt": 1770704467569,
      "commit": "https://github.com/openclaw/skills/commit/2fc03b376e9a7b77158c2bfb9042aea5f93266c2"
    },
    {
      "version": "1.0.6",
      "publishedAt": 1770608929890,
      "commit": "https://github.com/openclaw/skills/commit/21c331fe7d5437f0e0ae67980d573c09fd71019e"
    },
    {
      "version": "1.0.5",
      "publishedAt": 1770562972348,
      "commit": "https://github.com/openclaw/skills/commit/291ea334717f7152f4ebffcbda8d6b906b851c4e"
    },
    {
      "version": "1.0.3",
      "publishedAt": 1770501561307,
      "commit": "https://github.com/openclaw/skills/commit/fe6239d229bba519b487ef6d737e0bf744e4334b"
    }
  ]
}
